awt_ti/Backtest/__init__.py
awt_ti/Backtest/backtest.py
awt_ti/DataFetch/__init__.py
awt_ti/DataFetch/yfinance_data_fetcher.py
awt_ti/Indicators/__init__.py
awt_ti/Indicators/momentum/__init__.py
awt_ti/Indicators/momentum/momentum.py
awt_ti/Indicators/movingAverages/__init__.py
awt_ti/Indicators/movingAverages/movingAverages.py
awt_ti/Indicators/other/__init__.py
awt_ti/Indicators/other/other.py
awt_ti/Indicators/support_resistance/__init__.py
awt_ti/Indicators/support_resistance/support_resistance.py
awt_ti/Indicators/trend/__init__.py
awt_ti/Indicators/trend/trend.py
awt_ti/Indicators/volatility/__init__.py
awt_ti/Indicators/volatility/volatility.py
awt_ti/Indicators/volume/__init__.py
awt_ti/Indicators/volume/volume.py
awt_ti/Options/__init__.py
awt_ti/Options/yfinopts.py
awt_ti/__init__.py
awt_ti-0.1.0.dist-info/METADATA
awt_ti-0.1.0.dist-info/WHEEL
awt_ti-0.1.0.dist-info/entry_points.txt
awt_ti-0.1.0.dist-info/RECORD
