Metadata-Version: 2.3
Name: awt-ti
Version: 0.1.0
Summary: A comprehensive library for technical analysis indicators in financial markets
License: MIT
Keywords: finance,technical-analysis,trading,indicators,stocks
Author: William R. Astley
Author-email: william.astley@algebraicwealth.com
Requires-Python: >=3.11
Classifier: License :: OSI Approved :: MIT License
Classifier: Programming Language :: Python :: 3
Classifier: Programming Language :: Python :: 3.11
Classifier: Programming Language :: Python :: 3.12
Classifier: Programming Language :: Python :: 3.13
Requires-Dist: backtesting (>=0.6.2,<0.7.0)
Requires-Dist: furo (>=2024.8.6,<2025.0.0)
Requires-Dist: matplotlib (>=3.7.0,<4.0.0)
Requires-Dist: numpy (>=1.24.0,<2.0.0)
Requires-Dist: pandas (>=2.0.0,<3.0.0)
Requires-Dist: scipy (>=1.10.0,<2.0.0)
Requires-Dist: sphinx (>=8.2.1,<9.0.0)
Requires-Dist: sphinx-rtd-theme (>=3.0.2,<4.0.0)
Requires-Dist: toml (>=0.10.2,<0.11.0)
Requires-Dist: yahoo-fin (>=0.8.9.1,<0.9.0.0)
Requires-Dist: yahoo-finance (>=1.4.0,<2.0.0)
Requires-Dist: yfinance (>=0.2.54,<0.3.0)
Project-URL: Documentation, https://awt-ti.readthedocs.io
Project-URL: Repository, https://github.com/pr1m8/awt_ti
